setup.py
damienpuig/__init__.py
damienpuig/test.py
damienpuig.egg-info/PKG-INFO
damienpuig.egg-info/SOURCES.txt
damienpuig.egg-info/dependency_links.txt
damienpuig.egg-info/not-zip-safe
damienpuig.egg-info/requires.txt
damienpuig.egg-info/top_level.txt