Metadata-Version: 1.0
Name: damienpuig
Version: 0.1
Summary: The funniest joke
Home-page: http://github.com/damienpuig/library_test
Author: Damien PUIG
Author-email: damien.puig@gmail.com
License: MIT
Platform: UNKNOWN
